pysvb-0.2.0.dist-info/METADATA
pysvb-0.2.0.dist-info/WHEEL
pysvb/__init__.py
pysvb/__pycache__/test.cpython-311-pytest-7.4.2.pyc
pysvb/__pycache__/__init__.cpython-311.pyc
pysvb/test.py
pysvb/_lowlevel.cpython-311-darwin.so
pysvb-0.2.0.dist-info/RECORD
