Metadata-Version: 2.1
Name: pysvb
Version: 0.2.0
Requires-Dist: numpy >=1.25.2
Requires-Dist: opencv-python-headless >=4.8.0.76
Requires-Dist: pytest >=7.4.2
Summary: Add your description here
Author-email: Momo <39585852+imoken1122@users.noreply.github.com>
Requires-Python: >=3.11
